odoo/addons/contract_operating_unit_access_all/README.rst
odoo/addons/contract_operating_unit_access_all/__init__.py
odoo/addons/contract_operating_unit_access_all/__manifest__.py
odoo/addons/contract_operating_unit_access_all/i18n/contract_operating_unit_access_all.pot
odoo/addons/contract_operating_unit_access_all/readme/CONFIGURE.md
odoo/addons/contract_operating_unit_access_all/readme/CONTRIBUTORS.md
odoo/addons/contract_operating_unit_access_all/readme/DESCRIPTION.md
odoo/addons/contract_operating_unit_access_all/security/contract_security.xml
odoo/addons/contract_operating_unit_access_all/static/description/icon.png
odoo/addons/contract_operating_unit_access_all/static/description/index.html
odoo_addon_contract_operating_unit_access_all-17.0.1.0.0.2.dist-info/METADATA
odoo_addon_contract_operating_unit_access_all-17.0.1.0.0.2.dist-info/WHEEL
odoo_addon_contract_operating_unit_access_all-17.0.1.0.0.2.dist-info/top_level.txt
odoo_addon_contract_operating_unit_access_all-17.0.1.0.0.2.dist-info/RECORD
